AUTHORS
LICENSE
MANIFEST.in
README.txt
jeni.py
run_tests.py
setup.py
test_jeni.py
test_jeni_python2.py
test_jeni_python3.py
jeni.egg-info/PKG-INFO
jeni.egg-info/SOURCES.txt
jeni.egg-info/dependency_links.txt
jeni.egg-info/requires.txt
jeni.egg-info/top_level.txt